{
  "_comment": "Optional manual overrides to fix precinct name mismatches between results and boundary polygons.",
  "_format": "Map keys and values should be strings in the form \"COUNTY - PRECINCT\".",
  "_example": {
    "AIKEN - BREEZY NO. 87": "AIKEN - BREEZY HILL",
    "ANDERSON - BARKERS CREEK-MCADAMS": "ANDERSON - BARKERS CREEK"
  },
  "Saluda - Ridge Spring-Monetta": "SALUDA - RIDGE SPRINGMONETTA",
  "Berkeley - Carnes Cross Roads 2": "BERKELEY - CARNES CROSS ROAD 2",
  "Horry - Galivants Ferry": "HORRY - GALLIVANTS FERRY",
  "Richland - River Springs 1": "RICHLAND - RIVERSPRINGS 1",
  "Richland - River Springs 2": "RICHLAND - RIVERSPRINGS 2",
  "Richland - River Springs 3": "RICHLAND - RIVERSPRINGS 3",
  "Clarendon - Sardinia-Gable": "CLARENDON - SARDINA-GABLE",
  "Georgetown - Dreamkeepers": "GEORGETOWN - DREAM KEEPERS",
  "Florence - Coward No. 1": "FLORENCE - COWARDS NO. 1",
  "Florence - Coward No. 2": "FLORENCE - COWARDS NO. 2",
  "Dorchester - Miles-Jamison": "DORCHESTER - MILESJAMISON",
  "Saluda - Higgins-Zoar": "SALUDA - HIGGINSZOAR",
  "Lexington - St. Michaels": "LEXINGTON - ST. MICHAEL",
  "Fairfield - Jenkinsville": "FAIRFIELD - JEKINSVILLE",
  "Colleton - Hudsons Mill": "COLLETON - HUDSON MILL",
  "Charleston - Lincolnville": "CHARLESTON - LICOLNVILLE",
  "Anderson - Rock Springs": "ANDERSON - ROCK SPRING",
  "Anderson - North Pointe": "ANDERSON - NORTH POINT",
  "Lexington - Cedar Crest": "LEXINGTON - CEDARCREST",
  "Colleton - Wolf Creek": "COLLETON - WOLFE CREEK",
  "Laurens - Brewerton-Princeton": "LAURENS - BREWERTON - PRINCETON",
  "Pickens - Mcallister": "PICKENS - MCALISTER",
  "Greenwood - Newcastle": "GREENWOOD - NEW CASTLE",
  "Anderson - Coxs Creek": "ANDERSON - COX CREEK",
  "Spartanburg - Cavins-Hobbysville": "SPARTANBURG - CAVINS HOBBYSVILLE",
  "Orangeburg - Pinehill": "ORANGEBURG - PINE HILL",
  "Jasper - Okatie": "JASPER - OAKATIE",
  "Jasper - Okatie 2": "JASPER - OAKATIE 2",
  "Horry - Dog Bluff": "HORRY - DOGBLUFF",
  "Horry - Crescent": "HORRY - CRESENT",
  "Marlboro - Red Hill": "MARLBORO - REDHILL",
  "Clarendon - Wilson-Foreston": "CLARENDON - WILSON FORESTON",
  "Berkeley - Hilton Cross Road": "BERKELEY - HILTON CROSS RD",
  "Laurens - Barksdale-Narnie": "LAURENS - BARKSDALE-NARINE",
  "Cherokee - Littlejohns And Sarratt": "CHEROKEE - LITTLE JOHN AND SARRATTS",
  "Fairfield - Woodard": "FAIRFIELD - WOODWARD",
  "Chester - Lando/Landsford": "CHESTER - LANDO LANSFORD",
  "Oconee - Newry Corinth": "OCONEE - NEWRY-CORINTH",
  "Berkeley - Carnes Cross Road 1": "BERKELEY - CARNES CROSS ROADS 1",
  "Spartanburg - Drayton Fire Station": "SPARTANBURG - DAYTON FIRE STATION",
  "Lancaster - Gooch'S Cross Roads": "LANCASTER - GOOCHS CROSS ROAD",
  "Lancaster - Goochs Cross Roads": "LANCASTER - GOOCHS CROSS ROAD",
  "Lancaster - Mcilwain": "LANCASTER - MIDWAY",
  "Lancaster - Springdale": "LANCASTER - SPRING HILL",
  "Edgefield - Merriweather No.1": "EDGEFIELD - MERRIWEATHER NO. 1",
  "Edgefield - Merriweather No.2": "EDGEFIELD - MERRIWEATHER NO. 2",
  "Lexington - Redbank South #2": "LEXINGTON - RED BANK SOUTH 2",
  "Williamsburg - Kingstree No.1": "WILLIAMSBURG - KINGSTREE NO. 1",
  "Williamsburg - Kingstree No.2": "WILLIAMSBURG - KINGSTREE NO. 2",
  "Williamsburg - Kingstree No.3": "WILLIAMSBURG - KINGSTREE NO. 3",
  "Williamsburg - Kingstree No.4": "WILLIAMSBURG - KINGSTREE NO. 4",
  "Edgefield - Edgefield No.1": "EDGEFIELD - EDGEFIELD NO. 1",
  "Edgefield - Edgefield No.2": "EDGEFIELD - EDGEFIELD NO. 2",
  "Edgefield - Johnston No.1": "EDGEFIELD - JOHNSTON NO. 1",
  "Edgefield - Johnston No.2": "EDGEFIELD - JOHNSTON NO. 2",
  "Chester - Lando/Lansford": "CHESTER - LANDO LANSFORD",
  "Chesterfield - Angelus-Catarrh": "CHESTERFIELD - ANGELUS-CARARRH",
  "Chesterfield - Mt. Groghan": "CHESTERFIELD - MT. CROGHAN",
  "Edgefield - Trenton No.1": "EDGEFIELD - TRENTON NO. 1",
  "Edgefield - Trenton No.2": "EDGEFIELD - TRENTON NO. 2",
  "Cherokee - Littlejohn'S And Sarratt'S": "CHEROKEE - LITTLE JOHN AND SARRATTS",
  "Lexington - Pineridge #1": "LEXINGTON - PINE RIDGE 1",
  "Lexington - Pineridge #2": "LEXINGTON - PINE RIDGE 2",
  "Anderson - Fork No 1": "ANDERSON - FORK NO. 1",
  "Anderson - Fork No 2": "ANDERSON - FORK NO. 2",
  "Cherokee - 99 And Cherokee Falls": "CHEROKEE - NINETY NINE AND CHEROKEE FALLS",
  "Cherokee - Holly Grove-Buffalo": "CHEROKEE - HOLLY GROVE AND BUFFALO",
  "Fairfield - Gladden Grove": "FAIRFIELD - GARDEN GROVE",
  "Horry - 4 Mile": "HORRY - FOUR MILE",
  "Horry - Jernigans Xroads": "HORRY - JERIGANS CROSSROADS",
  "Laurens - Mt. Olive": "LAURENS - MOUNT OLIVE",
  "Newberry - Beth-Eden": "NEWBERRY - BETH - EDEN",
  "Newberry - Consolidated 5": "NEWBERRY - CONSOLIDATED NUMBER 5",
  "Spartanburg - Boiling Springs High": "SPARTANBURG - BOILING SPRINGS HIGH SCHOOL",
  "Spartanburg - Converse": "SPARTANBURG - CONVERSE FIRE STATION",
  "Spartanburg - Enoree 1St Baptist": "SPARTANBURG - ENOREE FIRST BAPTIST",
  "Spartanburg - Hayne": "SPARTANBURG - HAYNE BAPTIST",
  "Spartanburg - Mccracken Middle School": "SPARTANBURG - GABLE MIDDLE SCHOOL",
  "Spartanburg - Landrum": "SPARTANBURG - LANDRUM HIGH SCHOOL",
  "Spartanburg - Lyman": "SPARTANBURG - LYMAN TOWN HALL",
  "Spartanburg - Trinity Methodist Church": "SPARTANBURG - TRINITY METHODIST",
  "Spartanburg - Whitlock Junior High": "SPARTANBURG - WHITLOCK JR. HIGH"
}
