{"general":{"results":{"3":{"dem_votes":37282,"rep_votes":73807,"other_votes":36,"total_votes":111125,"dem_candidate":"Cheryl L Footman","rep_candidate":"Mark Hammond","margin":36525,"margin_pct":32.8684,"winner":"R","color":"#a50f15"},"2":{"dem_votes":34585,"rep_votes":75050,"other_votes":49,"total_votes":109684,"dem_candidate":"Cheryl L Footman","rep_candidate":"Mark Hammond","margin":40465,"margin_pct":36.8923,"winner":"R","color":"#a50f15"},"6":{"dem_votes":68919,"rep_votes":40589,"other_votes":52,"total_votes":109560,"dem_candidate":"Cheryl L Footman","rep_candidate":"Mark Hammond","margin":-28330,"margin_pct":-25.858,"winner":"D","color":"#4292c6"},"1":{"dem_votes":46981,"rep_votes":85195,"other_votes":51,"total_votes":132227,"dem_candidate":"Cheryl L Footman","rep_candidate":"Mark Hammond","margin":38214,"margin_pct":28.9003,"winner":"R","color":"#cb181d"},"5":{"dem_votes":41457,"rep_votes":58985,"other_votes":29,"total_votes":100471,"dem_candidate":"Cheryl L Footman","rep_candidate":"Mark Hammond","margin":17528,"margin_pct":17.4458,"winner":"R","color":"#ef3b2c"},"7":{"dem_votes":39445,"rep_votes":55945,"other_votes":27,"total_votes":95417,"dem_candidate":"Cheryl L Footman","rep_candidate":"Mark Hammond","margin":16500,"margin_pct":17.2925,"winner":"R","color":"#ef3b2c"},"4":{"dem_votes":27668,"rep_votes":63241,"other_votes":40,"total_votes":90949,"dem_candidate":"Cheryl L Footman","rep_candidate":"Mark Hammond","margin":35573,"margin_pct":39.1131,"winner":"R","color":"#a50f15"}}},"meta":{"match_coverage_pct":72.1811,"precinct_rows_total":2164,"precinct_rows_matched":1562,"precinct_rows_block_weighted":1562}}