{"general":{"results":{"10":{"dem_votes":9545,"rep_votes":15570,"other_votes":309,"total_votes":25424,"dem_candidate":"Barack Obama and Joe Biden","rep_candidate":"John McCain and Sarah Palin","margin":6025,"margin_pct":23.6981,"winner":"R","color":"#cb181d"},"4":{"dem_votes":9858,"rep_votes":18069,"other_votes":402,"total_votes":28329,"dem_candidate":"Barack Obama and Joe Biden","rep_candidate":"John McCain and Sarah Palin","margin":8211,"margin_pct":28.9844,"winner":"R","color":"#cb181d"},"25":{"dem_votes":8167,"rep_votes":18944,"other_votes":261,"total_votes":27372,"dem_candidate":"Barack Obama and Joe Biden","rep_candidate":"John McCain and Sarah Palin","margin":10777,"margin_pct":39.3724,"winner":"R","color":"#a50f15"},"24":{"dem_votes":11135,"rep_votes":23629,"other_votes":453,"total_votes":35217,"dem_candidate":"Barack Obama and Joe Biden","rep_candidate":"John McCain and Sarah Palin","margin":12494,"margin_pct":35.4772,"winner":"R","color":"#a50f15"},"26":{"dem_votes":12139,"rep_votes":15816,"other_votes":404,"total_votes":28359,"dem_candidate":"Barack Obama and Joe Biden","rep_candidate":"John McCain and Sarah Palin","margin":3677,"margin_pct":12.9659,"winner":"R","color":"#ef3b2c"},"40":{"dem_votes":19930,"rep_votes":15549,"other_votes":371,"total_votes":35850,"dem_candidate":"Barack Obama and Joe Biden","rep_candidate":"John McCain and Sarah Palin","margin":-4381,"margin_pct":-12.2204,"winner":"D","color":"#6baed6"},"45":{"dem_votes":16164,"rep_votes":10879,"other_votes":316,"total_votes":27359,"dem_candidate":"Barack Obama and Joe Biden","rep_candidate":"John McCain and Sarah Palin","margin":-5285,"margin_pct":-19.3172,"winner":"D","color":"#6baed6"},"3":{"dem_votes":9998,"rep_votes":26770,"other_votes":485,"total_votes":37253,"dem_candidate":"Barack Obama and Joe Biden","rep_candidate":"John McCain and Sarah Palin","margin":16772,"margin_pct":45.0219,"winner":"R","color":"#67000d"},"46":{"dem_votes":12835,"rep_votes":21728,"other_votes":379,"total_votes":34942,"dem_candidate":"Barack Obama and Joe Biden","rep_candidate":"John McCain and Sarah Palin","margin":8893,"margin_pct":25.4507,"winner":"R","color":"#cb181d"},"43":{"dem_votes":14614,"rep_votes":19771,"other_votes":426,"total_votes":34811,"dem_candidate":"Barack Obama and Joe Biden","rep_candidate":"John McCain and Sarah Palin","margin":5157,"margin_pct":14.8143,"winner":"R","color":"#ef3b2c"},"32":{"dem_votes":21138,"rep_votes":13665,"other_votes":343,"total_votes":35146,"dem_candidate":"Barack Obama and Joe Biden","rep_candidate":"John McCain and Sarah Palin","margin":-7473,"margin_pct":-21.2627,"winner":"D","color":"#4292c6"},"37":{"dem_votes":11471,"rep_votes":20831,"other_votes":428,"total_votes":32730,"dem_candidate":"Barack Obama and Joe Biden","rep_candidate":"John McCain and Sarah Palin","margin":9360,"margin_pct":28.5976,"winner":"R","color":"#cb181d"},"44":{"dem_votes":9796,"rep_votes":16713,"other_votes":317,"total_votes":26826,"dem_candidate":"Barack Obama and Joe Biden","rep_candidate":"John McCain and Sarah Palin","margin":6917,"margin_pct":25.7847,"winner":"R","color":"#cb181d"},"39":{"dem_votes":21444,"rep_votes":14252,"other_votes":398,"total_votes":36094,"dem_candidate":"Barack Obama and Joe Biden","rep_candidate":"John McCain and Sarah Palin","margin":-7192,"margin_pct":-19.9257,"winner":"D","color":"#6baed6"},"38":{"dem_votes":12228,"rep_votes":19311,"other_votes":423,"total_votes":31962,"dem_candidate":"Barack Obama and Joe Biden","rep_candidate":"John McCain and Sarah Palin","margin":7083,"margin_pct":22.1607,"winner":"R","color":"#cb181d"},"34":{"dem_votes":15830,"rep_votes":26190,"other_votes":544,"total_votes":42564,"dem_candidate":"Barack Obama and Joe Biden","rep_candidate":"John McCain and Sarah Palin","margin":10360,"margin_pct":24.3398,"winner":"R","color":"#cb181d"},"42":{"dem_votes":20634,"rep_votes":5556,"other_votes":374,"total_votes":26564,"dem_candidate":"Barack Obama and Joe Biden","rep_candidate":"John McCain and Sarah Palin","margin":-15078,"margin_pct":-56.761,"winner":"D","color":"#08519c"},"41":{"dem_votes":14488,"rep_votes":19941,"other_votes":543,"total_votes":34972,"dem_candidate":"Barack Obama and Joe Biden","rep_candidate":"John McCain and Sarah Palin","margin":5453,"margin_pct":15.5925,"winner":"R","color":"#ef3b2c"},"14":{"dem_votes":6829,"rep_votes":15236,"other_votes":288,"total_votes":22353,"dem_candidate":"Barack Obama and Joe Biden","rep_candidate":"John McCain and Sarah Palin","margin":8407,"margin_pct":37.6102,"winner":"R","color":"#a50f15"},"17":{"dem_votes":17707,"rep_votes":13605,"other_votes":418,"total_votes":31730,"dem_candidate":"Barack Obama and Joe Biden","rep_candidate":"John McCain and Sarah Palin","margin":-4102,"margin_pct":-12.9278,"winner":"D","color":"#6baed6"},"27":{"dem_votes":12991,"rep_votes":18412,"other_votes":407,"total_votes":31810,"dem_candidate":"Barack Obama and Joe Biden","rep_candidate":"John McCain and Sarah Palin","margin":5421,"margin_pct":17.0418,"winner":"R","color":"#ef3b2c"},"29":{"dem_votes":15409,"rep_votes":13925,"other_votes":339,"total_votes":29673,"dem_candidate":"Barack Obama and Joe Biden","rep_candidate":"John McCain and Sarah Palin","margin":-1484,"margin_pct":-5.0012,"winner":"D","color":"#9ecae1"},"36":{"dem_votes":17205,"rep_votes":14005,"other_votes":292,"total_votes":31502,"dem_candidate":"Barack Obama and Joe Biden","rep_candidate":"John McCain and Sarah Palin","margin":-3200,"margin_pct":-10.1581,"winner":"D","color":"#6baed6"},"31":{"dem_votes":12364,"rep_votes":22352,"other_votes":338,"total_votes":35054,"dem_candidate":"Barack Obama and Joe Biden","rep_candidate":"John McCain and Sarah Palin","margin":9988,"margin_pct":28.4932,"winner":"R","color":"#cb181d"},"28":{"dem_votes":12102,"rep_votes":19931,"other_votes":417,"total_votes":32450,"dem_candidate":"Barack Obama and Joe Biden","rep_candidate":"John McCain and Sarah Palin","margin":7829,"margin_pct":24.1263,"winner":"R","color":"#cb181d"},"30":{"dem_votes":19322,"rep_votes":11748,"other_votes":316,"total_votes":31386,"dem_candidate":"Barack Obama and Joe Biden","rep_candidate":"John McCain and Sarah Palin","margin":-7574,"margin_pct":-24.1318,"winner":"D","color":"#4292c6"},"7":{"dem_votes":18956,"rep_votes":11650,"other_votes":509,"total_votes":31115,"dem_candidate":"Barack Obama and Joe Biden","rep_candidate":"John McCain and Sarah Palin","margin":-7306,"margin_pct":-23.4806,"winner":"D","color":"#4292c6"},"6":{"dem_votes":11003,"rep_votes":25475,"other_votes":816,"total_votes":37294,"dem_candidate":"Barack Obama and Joe Biden","rep_candidate":"John McCain and Sarah Palin","margin":14472,"margin_pct":38.8052,"winner":"R","color":"#a50f15"},"12":{"dem_votes":6115,"rep_votes":15205,"other_votes":349,"total_votes":21669,"dem_candidate":"Barack Obama and Joe Biden","rep_candidate":"John McCain and Sarah Palin","margin":9090,"margin_pct":41.9493,"winner":"R","color":"#67000d"},"13":{"dem_votes":4997,"rep_votes":8625,"other_votes":229,"total_votes":13851,"dem_candidate":"Barack Obama and Joe Biden","rep_candidate":"John McCain and Sarah Palin","margin":3628,"margin_pct":26.1931,"winner":"R","color":"#cb181d"},"8":{"dem_votes":12598,"rep_votes":24525,"other_votes":631,"total_votes":37754,"dem_candidate":"Barack Obama and Joe Biden","rep_candidate":"John McCain and Sarah Palin","margin":11927,"margin_pct":31.5914,"winner":"R","color":"#a50f15"},"5":{"dem_votes":8194,"rep_votes":24595,"other_votes":686,"total_votes":33475,"dem_candidate":"Barack Obama and Joe Biden","rep_candidate":"John McCain and Sarah Palin","margin":16401,"margin_pct":48.9948,"winner":"R","color":"#67000d"},"9":{"dem_votes":10113,"rep_votes":18988,"other_votes":475,"total_votes":29576,"dem_candidate":"Barack Obama and Joe Biden","rep_candidate":"John McCain and Sarah Palin","margin":8875,"margin_pct":30.0074,"winner":"R","color":"#a50f15"},"33":{"dem_votes":11129,"rep_votes":19025,"other_votes":390,"total_votes":30544,"dem_candidate":"Barack Obama and Joe Biden","rep_candidate":"John McCain and Sarah Palin","margin":7896,"margin_pct":25.8512,"winner":"R","color":"#cb181d"},"35":{"dem_votes":13073,"rep_votes":17255,"other_votes":285,"total_votes":30613,"dem_candidate":"Barack Obama and Joe Biden","rep_candidate":"John McCain and Sarah Palin","margin":4182,"margin_pct":13.6609,"winner":"R","color":"#ef3b2c"},"22":{"dem_votes":18685,"rep_votes":16380,"other_votes":302,"total_votes":35367,"dem_candidate":"Barack Obama and Joe Biden","rep_candidate":"John McCain and Sarah Palin","margin":-2305,"margin_pct":-6.5174,"winner":"D","color":"#9ecae1"},"16":{"dem_votes":12967,"rep_votes":20520,"other_votes":429,"total_votes":33916,"dem_candidate":"Barack Obama and Joe Biden","rep_candidate":"John McCain and Sarah Palin","margin":7553,"margin_pct":22.2697,"winner":"R","color":"#cb181d"},"18":{"dem_votes":11378,"rep_votes":25633,"other_votes":379,"total_votes":37390,"dem_candidate":"Barack Obama and Joe Biden","rep_candidate":"John McCain and Sarah Palin","margin":14255,"margin_pct":38.1252,"winner":"R","color":"#a50f15"},"23":{"dem_votes":8017,"rep_votes":21429,"other_votes":375,"total_votes":29821,"dem_candidate":"Barack Obama and Joe Biden","rep_candidate":"John McCain and Sarah Palin","margin":13412,"margin_pct":44.975,"winner":"R","color":"#67000d"},"20":{"dem_votes":14826,"rep_votes":15604,"other_votes":388,"total_votes":30818,"dem_candidate":"Barack Obama and Joe Biden","rep_candidate":"John McCain and Sarah Palin","margin":778,"margin_pct":2.5245,"winner":"R","color":"#fcbba1"},"1":{"dem_votes":8360,"rep_votes":17786,"other_votes":445,"total_votes":26591,"dem_candidate":"Barack Obama and Joe Biden","rep_candidate":"John McCain and Sarah Palin","margin":9426,"margin_pct":35.4481,"winner":"R","color":"#a50f15"},"2":{"dem_votes":5827,"rep_votes":20040,"other_votes":535,"total_votes":26402,"dem_candidate":"Barack Obama and Joe Biden","rep_candidate":"John McCain and Sarah Palin","margin":14213,"margin_pct":53.833,"winner":"R","color":"#67000d"},"19":{"dem_votes":24432,"rep_votes":6596,"other_votes":271,"total_votes":31299,"dem_candidate":"Barack Obama and Joe Biden","rep_candidate":"John McCain and Sarah Palin","margin":-17836,"margin_pct":-56.9858,"winner":"D","color":"#08519c"},"21":{"dem_votes":24194,"rep_votes":8238,"other_votes":305,"total_votes":32737,"dem_candidate":"Barack Obama and Joe Biden","rep_candidate":"John McCain and Sarah Palin","margin":-15956,"margin_pct":-48.74,"winner":"D","color":"#08519c"},"11":{"dem_votes":4719,"rep_votes":6167,"other_votes":144,"total_votes":11030,"dem_candidate":"Barack Obama and Joe Biden","rep_candidate":"John McCain and Sarah Palin","margin":1448,"margin_pct":13.1278,"winner":"R","color":"#ef3b2c"},"15":{"dem_votes":10766,"rep_votes":16831,"other_votes":421,"total_votes":28018,"dem_candidate":"Barack Obama and Joe Biden","rep_candidate":"John McCain and Sarah Palin","margin":6065,"margin_pct":21.6468,"winner":"R","color":"#cb181d"}}},"meta":{"match_coverage_pct":92.0517,"precinct_rows_total":2013,"precinct_rows_matched":1853,"precinct_rows_block_weighted":1853}}