{"general":{"results":{"4":{"dem_votes":11267,"rep_votes":18815,"other_votes":60,"total_votes":30142,"dem_candidate":"Bob Conley","rep_candidate":"Lindsey Graham","margin":7548,"margin_pct":25.0415,"winner":"R","color":"#cb181d"},"24":{"dem_votes":10068,"rep_votes":21551,"other_votes":95,"total_votes":31714,"dem_candidate":"Bob Conley","rep_candidate":"Lindsey Graham","margin":11483,"margin_pct":36.208,"winner":"R","color":"#a50f15"},"25":{"dem_votes":8918,"rep_votes":16820,"other_votes":48,"total_votes":25786,"dem_candidate":"Bob Conley","rep_candidate":"Lindsey Graham","margin":7902,"margin_pct":30.6445,"winner":"R","color":"#a50f15"},"40":{"dem_votes":17912,"rep_votes":15771,"other_votes":29,"total_votes":33712,"dem_candidate":"Bob Conley","rep_candidate":"Lindsey Graham","margin":-2141,"margin_pct":-6.3509,"winner":"D","color":"#9ecae1"},"3":{"dem_votes":9670,"rep_votes":25679,"other_votes":93,"total_votes":35442,"dem_candidate":"Bob Conley","rep_candidate":"Lindsey Graham","margin":16009,"margin_pct":45.1696,"winner":"R","color":"#67000d"},"45":{"dem_votes":15266,"rep_votes":12606,"other_votes":23,"total_votes":27895,"dem_candidate":"Bob Conley","rep_candidate":"Lindsey Graham","margin":-2660,"margin_pct":-9.5358,"winner":"D","color":"#9ecae1"},"43":{"dem_votes":10995,"rep_votes":20514,"other_votes":98,"total_votes":31607,"dem_candidate":"Bob Conley","rep_candidate":"Lindsey Graham","margin":9519,"margin_pct":30.1167,"winner":"R","color":"#a50f15"},"46":{"dem_votes":6833,"rep_votes":14250,"other_votes":30,"total_votes":21113,"dem_candidate":"Bob Conley","rep_candidate":"Lindsey Graham","margin":7417,"margin_pct":35.13,"winner":"R","color":"#a50f15"},"32":{"dem_votes":19597,"rep_votes":16297,"other_votes":24,"total_votes":35918,"dem_candidate":"Bob Conley","rep_candidate":"Lindsey Graham","margin":-3300,"margin_pct":-9.1876,"winner":"D","color":"#9ecae1"},"37":{"dem_votes":7291,"rep_votes":15279,"other_votes":39,"total_votes":22609,"dem_candidate":"Bob Conley","rep_candidate":"Lindsey Graham","margin":7988,"margin_pct":35.3311,"winner":"R","color":"#a50f15"},"39":{"dem_votes":12838,"rep_votes":9144,"other_votes":21,"total_votes":22003,"dem_candidate":"Bob Conley","rep_candidate":"Lindsey Graham","margin":-3694,"margin_pct":-16.7886,"winner":"D","color":"#6baed6"},"44":{"dem_votes":7666,"rep_votes":16271,"other_votes":81,"total_votes":24018,"dem_candidate":"Bob Conley","rep_candidate":"Lindsey Graham","margin":8605,"margin_pct":35.8273,"winner":"R","color":"#a50f15"},"26":{"dem_votes":13854,"rep_votes":19252,"other_votes":61,"total_votes":33167,"dem_candidate":"Bob Conley","rep_candidate":"Lindsey Graham","margin":5398,"margin_pct":16.2752,"winner":"R","color":"#ef3b2c"},"36":{"dem_votes":18647,"rep_votes":19221,"other_votes":22,"total_votes":37890,"dem_candidate":"Bob Conley","rep_candidate":"Lindsey Graham","margin":574,"margin_pct":1.5149,"winner":"R","color":"#fcbba1"},"20":{"dem_votes":14624,"rep_votes":17351,"other_votes":180,"total_votes":32155,"dem_candidate":"Bob Conley","rep_candidate":"Lindsey Graham","margin":2727,"margin_pct":8.4808,"winner":"R","color":"#fc8a6a"},"42":{"dem_votes":14495,"rep_votes":6623,"other_votes":54,"total_votes":21172,"dem_candidate":"Bob Conley","rep_candidate":"Lindsey Graham","margin":-7872,"margin_pct":-37.1812,"winner":"D","color":"#2171b5"},"38":{"dem_votes":9777,"rep_votes":19128,"other_votes":80,"total_votes":28985,"dem_candidate":"Bob Conley","rep_candidate":"Lindsey Graham","margin":9351,"margin_pct":32.2615,"winner":"R","color":"#a50f15"},"41":{"dem_votes":7634,"rep_votes":13515,"other_votes":52,"total_votes":21201,"dem_candidate":"Bob Conley","rep_candidate":"Lindsey Graham","margin":5881,"margin_pct":27.7393,"winner":"R","color":"#cb181d"},"14":{"dem_votes":6560,"rep_votes":11813,"other_votes":30,"total_votes":18403,"dem_candidate":"Bob Conley","rep_candidate":"Lindsey Graham","margin":5253,"margin_pct":28.5443,"winner":"R","color":"#cb181d"},"17":{"dem_votes":16642,"rep_votes":12716,"other_votes":29,"total_votes":29387,"dem_candidate":"Bob Conley","rep_candidate":"Lindsey Graham","margin":-3926,"margin_pct":-13.3596,"winner":"D","color":"#6baed6"},"27":{"dem_votes":12607,"rep_votes":20927,"other_votes":31,"total_votes":33565,"dem_candidate":"Bob Conley","rep_candidate":"Lindsey Graham","margin":8320,"margin_pct":24.7877,"winner":"R","color":"#cb181d"},"29":{"dem_votes":18347,"rep_votes":19102,"other_votes":22,"total_votes":37471,"dem_candidate":"Bob Conley","rep_candidate":"Lindsey Graham","margin":755,"margin_pct":2.0149,"winner":"R","color":"#fcbba1"},"30":{"dem_votes":18015,"rep_votes":16721,"other_votes":30,"total_votes":34766,"dem_candidate":"Bob Conley","rep_candidate":"Lindsey Graham","margin":-1294,"margin_pct":-3.722,"winner":"D","color":"#c6dbef"},"31":{"dem_votes":11894,"rep_votes":24689,"other_votes":39,"total_votes":36622,"dem_candidate":"Bob Conley","rep_candidate":"Lindsey Graham","margin":12795,"margin_pct":34.938,"winner":"R","color":"#a50f15"},"34":{"dem_votes":8654,"rep_votes":21258,"other_votes":34,"total_votes":29946,"dem_candidate":"Bob Conley","rep_candidate":"Lindsey Graham","margin":12604,"margin_pct":42.0891,"winner":"R","color":"#67000d"},"7":{"dem_votes":17638,"rep_votes":11475,"other_votes":119,"total_votes":29232,"dem_candidate":"Bob Conley","rep_candidate":"Lindsey Graham","margin":-6163,"margin_pct":-21.0831,"winner":"D","color":"#4292c6"},"6":{"dem_votes":12250,"rep_votes":25879,"other_votes":295,"total_votes":38424,"dem_candidate":"Bob Conley","rep_candidate":"Lindsey Graham","margin":13629,"margin_pct":35.47,"winner":"R","color":"#a50f15"},"8":{"dem_votes":11446,"rep_votes":22494,"other_votes":200,"total_votes":34140,"dem_candidate":"Bob Conley","rep_candidate":"Lindsey Graham","margin":11048,"margin_pct":32.3609,"winner":"R","color":"#a50f15"},"13":{"dem_votes":3351,"rep_votes":5375,"other_votes":40,"total_votes":8766,"dem_candidate":"Bob Conley","rep_candidate":"Lindsey Graham","margin":2024,"margin_pct":23.0892,"winner":"R","color":"#cb181d"},"2":{"dem_votes":7366,"rep_votes":17744,"other_votes":102,"total_votes":25212,"dem_candidate":"Bob Conley","rep_candidate":"Lindsey Graham","margin":10378,"margin_pct":41.1629,"winner":"R","color":"#67000d"},"12":{"dem_votes":3475,"rep_votes":8151,"other_votes":53,"total_votes":11679,"dem_candidate":"Bob Conley","rep_candidate":"Lindsey Graham","margin":4676,"margin_pct":40.0377,"winner":"R","color":"#67000d"},"5":{"dem_votes":9097,"rep_votes":20562,"other_votes":199,"total_votes":29858,"dem_candidate":"Bob Conley","rep_candidate":"Lindsey Graham","margin":11465,"margin_pct":38.3984,"winner":"R","color":"#a50f15"},"9":{"dem_votes":11419,"rep_votes":19505,"other_votes":96,"total_votes":31020,"dem_candidate":"Bob Conley","rep_candidate":"Lindsey Graham","margin":8086,"margin_pct":26.0671,"winner":"R","color":"#cb181d"},"10":{"dem_votes":7043,"rep_votes":21137,"other_votes":40,"total_votes":28220,"dem_candidate":"Bob Conley","rep_candidate":"Lindsey Graham","margin":14094,"margin_pct":49.9433,"winner":"R","color":"#67000d"},"28":{"dem_votes":8623,"rep_votes":18192,"other_votes":27,"total_votes":26842,"dem_candidate":"Bob Conley","rep_candidate":"Lindsey Graham","margin":9569,"margin_pct":35.6494,"winner":"R","color":"#a50f15"},"33":{"dem_votes":8181,"rep_votes":14357,"other_votes":30,"total_votes":22568,"dem_candidate":"Bob Conley","rep_candidate":"Lindsey Graham","margin":6176,"margin_pct":27.3662,"winner":"R","color":"#cb181d"},"35":{"dem_votes":11466,"rep_votes":14705,"other_votes":18,"total_votes":26189,"dem_candidate":"Bob Conley","rep_candidate":"Lindsey Graham","margin":3239,"margin_pct":12.3678,"winner":"R","color":"#ef3b2c"},"16":{"dem_votes":6127,"rep_votes":14056,"other_votes":29,"total_votes":20212,"dem_candidate":"Bob Conley","rep_candidate":"Lindsey Graham","margin":7929,"margin_pct":39.2292,"winner":"R","color":"#a50f15"},"18":{"dem_votes":7478,"rep_votes":18508,"other_votes":25,"total_votes":26011,"dem_candidate":"Bob Conley","rep_candidate":"Lindsey Graham","margin":11030,"margin_pct":42.4051,"winner":"R","color":"#67000d"},"23":{"dem_votes":6264,"rep_votes":19786,"other_votes":33,"total_votes":26083,"dem_candidate":"Bob Conley","rep_candidate":"Lindsey Graham","margin":13522,"margin_pct":51.8422,"winner":"R","color":"#67000d"},"1":{"dem_votes":6413,"rep_votes":17305,"other_votes":34,"total_votes":23752,"dem_candidate":"Bob Conley","rep_candidate":"Lindsey Graham","margin":10892,"margin_pct":45.8572,"winner":"R","color":"#67000d"},"22":{"dem_votes":11939,"rep_votes":18752,"other_votes":45,"total_votes":30736,"dem_candidate":"Bob Conley","rep_candidate":"Lindsey Graham","margin":6813,"margin_pct":22.1662,"winner":"R","color":"#cb181d"},"19":{"dem_votes":17936,"rep_votes":9259,"other_votes":31,"total_votes":27226,"dem_candidate":"Bob Conley","rep_candidate":"Lindsey Graham","margin":-8677,"margin_pct":-31.8703,"winner":"D","color":"#2171b5"},"21":{"dem_votes":19782,"rep_votes":13354,"other_votes":73,"total_votes":33209,"dem_candidate":"Bob Conley","rep_candidate":"Lindsey Graham","margin":-6428,"margin_pct":-19.3562,"winner":"D","color":"#6baed6"},"15":{"dem_votes":8643,"rep_votes":17081,"other_votes":47,"total_votes":25771,"dem_candidate":"Bob Conley","rep_candidate":"Lindsey Graham","margin":8438,"margin_pct":32.7422,"winner":"R","color":"#a50f15"}}},"meta":{"match_coverage_pct":86.0188,"precinct_rows_total":2017,"precinct_rows_matched":1735,"precinct_rows_block_weighted":0}}