{"general":{"results":{"11":{"dem_votes":2744,"rep_votes":7972,"other_votes":5,"total_votes":10721,"dem_candidate":"Krystle Matthews","rep_candidate":"Tim Scott","margin":5228,"margin_pct":48.7641,"winner":"R","color":"#67000d"},"81":{"dem_votes":4773,"rep_votes":10929,"other_votes":15,"total_votes":15717,"dem_candidate":"Krystle Matthews","rep_candidate":"Tim Scott","margin":6156,"margin_pct":39.1678,"winner":"R","color":"#a50f15"},"82":{"dem_votes":4429,"rep_votes":5610,"other_votes":16,"total_votes":10055,"dem_candidate":"Krystle Matthews","rep_candidate":"Tim Scott","margin":1181,"margin_pct":11.7454,"winner":"R","color":"#ef3b2c"},"84":{"dem_votes":3493,"rep_votes":7960,"other_votes":4,"total_votes":11457,"dem_candidate":"Krystle Matthews","rep_candidate":"Tim Scott","margin":4467,"margin_pct":38.9893,"winner":"R","color":"#a50f15"},"83":{"dem_votes":3371,"rep_votes":9679,"other_votes":12,"total_votes":13062,"dem_candidate":"Krystle Matthews","rep_candidate":"Tim Scott","margin":6308,"margin_pct":48.2928,"winner":"R","color":"#67000d"},"86":{"dem_votes":3823,"rep_votes":9172,"other_votes":16,"total_votes":13011,"dem_candidate":"Krystle Matthews","rep_candidate":"Tim Scott","margin":5349,"margin_pct":41.1114,"winner":"R","color":"#67000d"},"91":{"dem_votes":3689,"rep_votes":4488,"other_votes":3,"total_votes":8180,"dem_candidate":"Krystle Matthews","rep_candidate":"Tim Scott","margin":799,"margin_pct":9.7677,"winner":"R","color":"#fc8a6a"},"6":{"dem_votes":3810,"rep_votes":12099,"other_votes":27,"total_votes":15936,"dem_candidate":"Krystle Matthews","rep_candidate":"Tim Scott","margin":8289,"margin_pct":52.0143,"winner":"R","color":"#67000d"},"9":{"dem_votes":3336,"rep_votes":8736,"other_votes":14,"total_votes":12086,"dem_candidate":"Krystle Matthews","rep_candidate":"Tim Scott","margin":5400,"margin_pct":44.6798,"winner":"R","color":"#67000d"},"8":{"dem_votes":3027,"rep_votes":9584,"other_votes":9,"total_votes":12620,"dem_candidate":"Krystle Matthews","rep_candidate":"Tim Scott","margin":6557,"margin_pct":51.9572,"winner":"R","color":"#67000d"},"7":{"dem_votes":1734,"rep_votes":8114,"other_votes":10,"total_votes":9858,"dem_candidate":"Krystle Matthews","rep_candidate":"Tim Scott","margin":6380,"margin_pct":64.719,"winner":"R","color":"#67000d"},"10":{"dem_votes":3247,"rep_votes":11023,"other_votes":15,"total_votes":14285,"dem_candidate":"Krystle Matthews","rep_candidate":"Tim Scott","margin":7776,"margin_pct":54.4347,"winner":"R","color":"#67000d"},"90":{"dem_votes":4032,"rep_votes":6347,"other_votes":7,"total_votes":10386,"dem_candidate":"Krystle Matthews","rep_candidate":"Tim Scott","margin":2315,"margin_pct":22.2896,"winner":"R","color":"#cb181d"},"124":{"dem_votes":4971,"rep_votes":8460,"other_votes":11,"total_votes":13442,"dem_candidate":"Krystle Matthews","rep_candidate":"Tim Scott","margin":3489,"margin_pct":25.956,"winner":"R","color":"#cb181d"},"120":{"dem_votes":6157,"rep_votes":12331,"other_votes":11,"total_votes":18499,"dem_candidate":"Krystle Matthews","rep_candidate":"Tim Scott","margin":6174,"margin_pct":33.3748,"winner":"R","color":"#a50f15"},"118":{"dem_votes":7476,"rep_votes":13411,"other_votes":6,"total_votes":20893,"dem_candidate":"Krystle Matthews","rep_candidate":"Tim Scott","margin":5935,"margin_pct":28.4066,"winner":"R","color":"#cb181d"},"121":{"dem_votes":3807,"rep_votes":3440,"other_votes":5,"total_votes":7252,"dem_candidate":"Krystle Matthews","rep_candidate":"Tim Scott","margin":-367,"margin_pct":-5.0607,"winner":"D","color":"#9ecae1"},"123":{"dem_votes":6319,"rep_votes":11628,"other_votes":14,"total_votes":17961,"dem_candidate":"Krystle Matthews","rep_candidate":"Tim Scott","margin":5309,"margin_pct":29.5585,"winner":"R","color":"#cb181d"},"102":{"dem_votes":5925,"rep_votes":7085,"other_votes":4,"total_votes":13014,"dem_candidate":"Krystle Matthews","rep_candidate":"Tim Scott","margin":1160,"margin_pct":8.9135,"winner":"R","color":"#fc8a6a"},"100":{"dem_votes":7121,"rep_votes":14195,"other_votes":21,"total_votes":21337,"dem_candidate":"Krystle Matthews","rep_candidate":"Tim Scott","margin":7074,"margin_pct":33.1537,"winner":"R","color":"#a50f15"},"117":{"dem_votes":5101,"rep_votes":5551,"other_votes":17,"total_votes":10669,"dem_candidate":"Krystle Matthews","rep_candidate":"Tim Scott","margin":450,"margin_pct":4.2178,"winner":"R","color":"#fcbba1"},"15":{"dem_votes":3222,"rep_votes":4047,"other_votes":9,"total_votes":7278,"dem_candidate":"Krystle Matthews","rep_candidate":"Tim Scott","margin":825,"margin_pct":11.3355,"winner":"R","color":"#ef3b2c"},"92":{"dem_votes":4405,"rep_votes":7873,"other_votes":13,"total_votes":12291,"dem_candidate":"Krystle Matthews","rep_candidate":"Tim Scott","margin":3468,"margin_pct":28.2158,"winner":"R","color":"#cb181d"},"99":{"dem_votes":6459,"rep_votes":13130,"other_votes":24,"total_votes":19613,"dem_candidate":"Krystle Matthews","rep_candidate":"Tim Scott","margin":6671,"margin_pct":34.0132,"winner":"R","color":"#a50f15"},"30":{"dem_votes":2119,"rep_votes":8534,"other_votes":7,"total_votes":10660,"dem_candidate":"Krystle Matthews","rep_candidate":"Tim Scott","margin":6415,"margin_pct":60.1782,"winner":"R","color":"#67000d"},"53":{"dem_votes":3278,"rep_votes":5902,"other_votes":4,"total_votes":9184,"dem_candidate":"Krystle Matthews","rep_candidate":"Tim Scott","margin":2624,"margin_pct":28.5714,"winner":"R","color":"#cb181d"},"93":{"dem_votes":5605,"rep_votes":6316,"other_votes":15,"total_votes":11936,"dem_candidate":"Krystle Matthews","rep_candidate":"Tim Scott","margin":711,"margin_pct":5.9568,"winner":"R","color":"#fc8a6a"},"108":{"dem_votes":8419,"rep_votes":17936,"other_votes":22,"total_votes":26377,"dem_candidate":"Krystle Matthews","rep_candidate":"Tim Scott","margin":9517,"margin_pct":36.0807,"winner":"R","color":"#a50f15"},"110":{"dem_votes":6066,"rep_votes":9726,"other_votes":18,"total_votes":15810,"dem_candidate":"Krystle Matthews","rep_candidate":"Tim Scott","margin":3660,"margin_pct":23.1499,"winner":"R","color":"#cb181d"},"111":{"dem_votes":7496,"rep_votes":2888,"other_votes":22,"total_votes":10406,"dem_candidate":"Krystle Matthews","rep_candidate":"Tim Scott","margin":-4608,"margin_pct":-44.2821,"winner":"D","color":"#08519c"},"116":{"dem_votes":8065,"rep_votes":9442,"other_votes":8,"total_votes":17515,"dem_candidate":"Krystle Matthews","rep_candidate":"Tim Scott","margin":1377,"margin_pct":7.8618,"winner":"R","color":"#fc8a6a"},"115":{"dem_votes":9173,"rep_votes":10847,"other_votes":39,"total_votes":20059,"dem_candidate":"Krystle Matthews","rep_candidate":"Tim Scott","margin":1674,"margin_pct":8.3454,"winner":"R","color":"#fc8a6a"},"112":{"dem_votes":8040,"rep_votes":13758,"other_votes":31,"total_votes":21829,"dem_candidate":"Krystle Matthews","rep_candidate":"Tim Scott","margin":5718,"margin_pct":26.1945,"winner":"R","color":"#cb181d"},"119":{"dem_votes":8008,"rep_votes":7970,"other_votes":36,"total_votes":16014,"dem_candidate":"Krystle Matthews","rep_candidate":"Tim Scott","margin":-38,"margin_pct":-0.2373,"winner":"D","color":"#c6dbef"},"113":{"dem_votes":6644,"rep_votes":3408,"other_votes":20,"total_votes":10072,"dem_candidate":"Krystle Matthews","rep_candidate":"Tim Scott","margin":-3236,"margin_pct":-32.1287,"winner":"D","color":"#2171b5"},"109":{"dem_votes":5279,"rep_votes":2986,"other_votes":20,"total_votes":8285,"dem_candidate":"Krystle Matthews","rep_candidate":"Tim Scott","margin":-2293,"margin_pct":-27.6765,"winner":"D","color":"#4292c6"},"114":{"dem_votes":7081,"rep_votes":10282,"other_votes":25,"total_votes":17388,"dem_candidate":"Krystle Matthews","rep_candidate":"Tim Scott","margin":3201,"margin_pct":18.4092,"winner":"R","color":"#ef3b2c"},"29":{"dem_votes":2814,"rep_votes":9768,"other_votes":9,"total_votes":12591,"dem_candidate":"Krystle Matthews","rep_candidate":"Tim Scott","margin":6954,"margin_pct":55.2299,"winner":"R","color":"#67000d"},"41":{"dem_votes":7374,"rep_votes":5655,"other_votes":16,"total_votes":13045,"dem_candidate":"Krystle Matthews","rep_candidate":"Tim Scott","margin":-1719,"margin_pct":-13.1775,"winner":"D","color":"#6baed6"},"43":{"dem_votes":3417,"rep_votes":8305,"other_votes":4,"total_votes":11726,"dem_candidate":"Krystle Matthews","rep_candidate":"Tim Scott","margin":4888,"margin_pct":41.6851,"winner":"R","color":"#67000d"},"65":{"dem_votes":2462,"rep_votes":7695,"other_votes":6,"total_votes":10163,"dem_candidate":"Krystle Matthews","rep_candidate":"Tim Scott","margin":5233,"margin_pct":51.4907,"winner":"R","color":"#67000d"},"54":{"dem_votes":3467,"rep_votes":4624,"other_votes":11,"total_votes":8102,"dem_candidate":"Krystle Matthews","rep_candidate":"Tim Scott","margin":1157,"margin_pct":14.2804,"winner":"R","color":"#ef3b2c"},"64":{"dem_votes":5025,"rep_votes":6124,"other_votes":7,"total_votes":11156,"dem_candidate":"Krystle Matthews","rep_candidate":"Tim Scott","margin":1099,"margin_pct":9.8512,"winner":"R","color":"#fc8a6a"},"101":{"dem_votes":5718,"rep_votes":5032,"other_votes":3,"total_votes":10753,"dem_candidate":"Krystle Matthews","rep_candidate":"Tim Scott","margin":-686,"margin_pct":-6.3796,"winner":"D","color":"#9ecae1"},"97":{"dem_votes":5306,"rep_votes":10163,"other_votes":10,"total_votes":15479,"dem_candidate":"Krystle Matthews","rep_candidate":"Tim Scott","margin":4857,"margin_pct":31.378,"winner":"R","color":"#a50f15"},"62":{"dem_votes":5029,"rep_votes":4600,"other_votes":7,"total_votes":9636,"dem_candidate":"Krystle Matthews","rep_candidate":"Tim Scott","margin":-429,"margin_pct":-4.4521,"winner":"D","color":"#c6dbef"},"60":{"dem_votes":3744,"rep_votes":7258,"other_votes":5,"total_votes":11007,"dem_candidate":"Krystle Matthews","rep_candidate":"Tim Scott","margin":3514,"margin_pct":31.9251,"winner":"R","color":"#a50f15"},"59":{"dem_votes":6157,"rep_votes":3550,"other_votes":4,"total_votes":9711,"dem_candidate":"Krystle Matthews","rep_candidate":"Tim Scott","margin":-2607,"margin_pct":-26.8458,"winner":"D","color":"#4292c6"},"55":{"dem_votes":3584,"rep_votes":5070,"other_votes":6,"total_votes":8660,"dem_candidate":"Krystle Matthews","rep_candidate":"Tim Scott","margin":1486,"margin_pct":17.1594,"winner":"R","color":"#ef3b2c"},"57":{"dem_votes":3360,"rep_votes":3156,"other_votes":4,"total_votes":6520,"dem_candidate":"Krystle Matthews","rep_candidate":"Tim Scott","margin":-204,"margin_pct":-3.1288,"winner":"D","color":"#c6dbef"},"98":{"dem_votes":5599,"rep_votes":7790,"other_votes":18,"total_votes":13407,"dem_candidate":"Krystle Matthews","rep_candidate":"Tim Scott","margin":2191,"margin_pct":16.3422,"winner":"R","color":"#ef3b2c"},"94":{"dem_votes":4037,"rep_votes":7873,"other_votes":12,"total_votes":11922,"dem_candidate":"Krystle Matthews","rep_candidate":"Tim Scott","margin":3836,"margin_pct":32.1758,"winner":"R","color":"#a50f15"},"61":{"dem_votes":4060,"rep_votes":6322,"other_votes":15,"total_votes":10397,"dem_candidate":"Krystle Matthews","rep_candidate":"Tim Scott","margin":2262,"margin_pct":21.7563,"winner":"R","color":"#cb181d"},"63":{"dem_votes":4135,"rep_votes":8857,"other_votes":11,"total_votes":13003,"dem_candidate":"Krystle Matthews","rep_candidate":"Tim Scott","margin":4722,"margin_pct":36.3147,"winner":"R","color":"#a50f15"},"103":{"dem_votes":5382,"rep_votes":5316,"other_votes":3,"total_votes":10701,"dem_candidate":"Krystle Matthews","rep_candidate":"Tim Scott","margin":-66,"margin_pct":-0.6168,"winner":"D","color":"#c6dbef"},"19":{"dem_votes":3686,"rep_votes":6930,"other_votes":23,"total_votes":10639,"dem_candidate":"Krystle Matthews","rep_candidate":"Tim Scott","margin":3244,"margin_pct":30.4916,"winner":"R","color":"#a50f15"},"21":{"dem_votes":4344,"rep_votes":11180,"other_votes":19,"total_votes":15543,"dem_candidate":"Krystle Matthews","rep_candidate":"Tim Scott","margin":6836,"margin_pct":43.9812,"winner":"R","color":"#67000d"},"20":{"dem_votes":3493,"rep_votes":8854,"other_votes":25,"total_votes":12372,"dem_candidate":"Krystle Matthews","rep_candidate":"Tim Scott","margin":5361,"margin_pct":43.3317,"winner":"R","color":"#67000d"},"28":{"dem_votes":5277,"rep_votes":11401,"other_votes":22,"total_votes":16700,"dem_candidate":"Krystle Matthews","rep_candidate":"Tim Scott","margin":6124,"margin_pct":36.6707,"winner":"R","color":"#a50f15"},"25":{"dem_votes":4910,"rep_votes":3016,"other_votes":6,"total_votes":7932,"dem_candidate":"Krystle Matthews","rep_candidate":"Tim Scott","margin":-1894,"margin_pct":-23.878,"winner":"D","color":"#4292c6"},"35":{"dem_votes":5443,"rep_votes":14198,"other_votes":27,"total_votes":19668,"dem_candidate":"Krystle Matthews","rep_candidate":"Tim Scott","margin":8755,"margin_pct":44.5139,"winner":"R","color":"#67000d"},"22":{"dem_votes":4898,"rep_votes":9502,"other_votes":31,"total_votes":14431,"dem_candidate":"Krystle Matthews","rep_candidate":"Tim Scott","margin":4604,"margin_pct":31.9035,"winner":"R","color":"#a50f15"},"27":{"dem_votes":5244,"rep_votes":9605,"other_votes":27,"total_votes":14876,"dem_candidate":"Krystle Matthews","rep_candidate":"Tim Scott","margin":4361,"margin_pct":29.3157,"winner":"R","color":"#cb181d"},"18":{"dem_votes":4119,"rep_votes":12952,"other_votes":29,"total_votes":17100,"dem_candidate":"Krystle Matthews","rep_candidate":"Tim Scott","margin":8833,"margin_pct":51.655,"winner":"R","color":"#67000d"},"24":{"dem_votes":7021,"rep_votes":12005,"other_votes":46,"total_votes":19072,"dem_candidate":"Krystle Matthews","rep_candidate":"Tim Scott","margin":4984,"margin_pct":26.1326,"winner":"R","color":"#cb181d"},"17":{"dem_votes":3327,"rep_votes":13779,"other_votes":39,"total_votes":17145,"dem_candidate":"Krystle Matthews","rep_candidate":"Tim Scott","margin":10452,"margin_pct":60.9624,"winner":"R","color":"#67000d"},"16":{"dem_votes":4780,"rep_votes":10242,"other_votes":21,"total_votes":15043,"dem_candidate":"Krystle Matthews","rep_candidate":"Tim Scott","margin":5462,"margin_pct":36.3092,"winner":"R","color":"#a50f15"},"23":{"dem_votes":5973,"rep_votes":4313,"other_votes":28,"total_votes":10314,"dem_candidate":"Krystle Matthews","rep_candidate":"Tim Scott","margin":-1660,"margin_pct":-16.0946,"winner":"D","color":"#6baed6"},"36":{"dem_votes":3567,"rep_votes":8952,"other_votes":15,"total_votes":12534,"dem_candidate":"Krystle Matthews","rep_candidate":"Tim Scott","margin":5385,"margin_pct":42.9631,"winner":"R","color":"#67000d"},"13":{"dem_votes":3401,"rep_votes":10369,"other_votes":10,"total_votes":13780,"dem_candidate":"Krystle Matthews","rep_candidate":"Tim Scott","margin":6968,"margin_pct":50.566,"winner":"R","color":"#67000d"},"12":{"dem_votes":4633,"rep_votes":5583,"other_votes":2,"total_votes":10218,"dem_candidate":"Krystle Matthews","rep_candidate":"Tim Scott","margin":950,"margin_pct":9.2973,"winner":"R","color":"#fc8a6a"},"14":{"dem_votes":3163,"rep_votes":10206,"other_votes":19,"total_votes":13388,"dem_candidate":"Krystle Matthews","rep_candidate":"Tim Scott","margin":7043,"margin_pct":52.6068,"winner":"R","color":"#67000d"},"122":{"dem_votes":4126,"rep_votes":4211,"other_votes":3,"total_votes":8340,"dem_candidate":"Krystle Matthews","rep_candidate":"Tim Scott","margin":85,"margin_pct":1.0192,"winner":"R","color":"#fcbba1"},"105":{"dem_votes":3466,"rep_votes":10964,"other_votes":12,"total_votes":14442,"dem_candidate":"Krystle Matthews","rep_candidate":"Tim Scott","margin":7498,"margin_pct":51.918,"winner":"R","color":"#67000d"},"104":{"dem_votes":4931,"rep_votes":15281,"other_votes":4,"total_votes":20216,"dem_candidate":"Krystle Matthews","rep_candidate":"Tim Scott","margin":10350,"margin_pct":51.1971,"winner":"R","color":"#67000d"},"58":{"dem_votes":3634,"rep_votes":10842,"other_votes":4,"total_votes":14480,"dem_candidate":"Krystle Matthews","rep_candidate":"Tim Scott","margin":7208,"margin_pct":49.779,"winner":"R","color":"#67000d"},"106":{"dem_votes":6143,"rep_votes":17773,"other_votes":9,"total_votes":23925,"dem_candidate":"Krystle Matthews","rep_candidate":"Tim Scott","margin":11630,"margin_pct":48.6102,"winner":"R","color":"#67000d"},"56":{"dem_votes":5754,"rep_votes":12934,"other_votes":7,"total_votes":18695,"dem_candidate":"Krystle Matthews","rep_candidate":"Tim Scott","margin":7180,"margin_pct":38.406,"winner":"R","color":"#a50f15"},"107":{"dem_votes":5718,"rep_votes":12735,"other_votes":12,"total_votes":18465,"dem_candidate":"Krystle Matthews","rep_candidate":"Tim Scott","margin":7017,"margin_pct":38.0016,"winner":"R","color":"#a50f15"},"68":{"dem_votes":4612,"rep_votes":11128,"other_votes":14,"total_votes":15754,"dem_candidate":"Krystle Matthews","rep_candidate":"Tim Scott","margin":6516,"margin_pct":41.3609,"winner":"R","color":"#67000d"},"52":{"dem_votes":4917,"rep_votes":10013,"other_votes":9,"total_votes":14939,"dem_candidate":"Krystle Matthews","rep_candidate":"Tim Scott","margin":5096,"margin_pct":34.1121,"winner":"R","color":"#a50f15"},"50":{"dem_votes":5937,"rep_votes":5147,"other_votes":7,"total_votes":11091,"dem_candidate":"Krystle Matthews","rep_candidate":"Tim Scott","margin":-790,"margin_pct":-7.1229,"winner":"D","color":"#9ecae1"},"80":{"dem_votes":7071,"rep_votes":5119,"other_votes":12,"total_votes":12202,"dem_candidate":"Krystle Matthews","rep_candidate":"Tim Scott","margin":-1952,"margin_pct":-15.9974,"winner":"D","color":"#6baed6"},"45":{"dem_votes":9743,"rep_votes":17503,"other_votes":18,"total_votes":27264,"dem_candidate":"Krystle Matthews","rep_candidate":"Tim Scott","margin":7760,"margin_pct":28.4624,"winner":"R","color":"#cb181d"},"44":{"dem_votes":2469,"rep_votes":5695,"other_votes":3,"total_votes":8167,"dem_candidate":"Krystle Matthews","rep_candidate":"Tim Scott","margin":3226,"margin_pct":39.5004,"winner":"R","color":"#a50f15"},"42":{"dem_votes":2971,"rep_votes":7009,"other_votes":6,"total_votes":9986,"dem_candidate":"Krystle Matthews","rep_candidate":"Tim Scott","margin":4038,"margin_pct":40.4366,"winner":"R","color":"#67000d"},"85":{"dem_votes":5823,"rep_votes":12003,"other_votes":21,"total_votes":17847,"dem_candidate":"Krystle Matthews","rep_candidate":"Tim Scott","margin":6180,"margin_pct":34.6277,"winner":"R","color":"#a50f15"},"87":{"dem_votes":5196,"rep_votes":17546,"other_votes":26,"total_votes":22768,"dem_candidate":"Krystle Matthews","rep_candidate":"Tim Scott","margin":12350,"margin_pct":54.2428,"winner":"R","color":"#67000d"},"39":{"dem_votes":2736,"rep_votes":10399,"other_votes":4,"total_votes":13139,"dem_candidate":"Krystle Matthews","rep_candidate":"Tim Scott","margin":7663,"margin_pct":58.3226,"winner":"R","color":"#67000d"},"96":{"dem_votes":2322,"rep_votes":6302,"other_votes":11,"total_votes":8635,"dem_candidate":"Krystle Matthews","rep_candidate":"Tim Scott","margin":3980,"margin_pct":46.0915,"winner":"R","color":"#67000d"},"89":{"dem_votes":4484,"rep_votes":6920,"other_votes":21,"total_votes":11425,"dem_candidate":"Krystle Matthews","rep_candidate":"Tim Scott","margin":2436,"margin_pct":21.3217,"winner":"R","color":"#cb181d"},"88":{"dem_votes":3787,"rep_votes":9444,"other_votes":10,"total_votes":13241,"dem_candidate":"Krystle Matthews","rep_candidate":"Tim Scott","margin":5657,"margin_pct":42.7234,"winner":"R","color":"#67000d"},"69":{"dem_votes":4028,"rep_votes":8649,"other_votes":17,"total_votes":12694,"dem_candidate":"Krystle Matthews","rep_candidate":"Tim Scott","margin":4621,"margin_pct":36.403,"winner":"R","color":"#a50f15"},"71":{"dem_votes":6962,"rep_votes":12624,"other_votes":25,"total_votes":19611,"dem_candidate":"Krystle Matthews","rep_candidate":"Tim Scott","margin":5662,"margin_pct":28.8716,"winner":"R","color":"#cb181d"},"40":{"dem_votes":3774,"rep_votes":8963,"other_votes":10,"total_votes":12747,"dem_candidate":"Krystle Matthews","rep_candidate":"Tim Scott","margin":5189,"margin_pct":40.7076,"winner":"R","color":"#67000d"},"2":{"dem_votes":3475,"rep_votes":11129,"other_votes":9,"total_votes":14613,"dem_candidate":"Krystle Matthews","rep_candidate":"Tim Scott","margin":7654,"margin_pct":52.378,"winner":"R","color":"#67000d"},"1":{"dem_votes":2491,"rep_votes":11740,"other_votes":12,"total_votes":14243,"dem_candidate":"Krystle Matthews","rep_candidate":"Tim Scott","margin":9249,"margin_pct":64.9372,"winner":"R","color":"#67000d"},"66":{"dem_votes":6359,"rep_votes":3990,"other_votes":5,"total_votes":10354,"dem_candidate":"Krystle Matthews","rep_candidate":"Tim Scott","margin":-2369,"margin_pct":-22.88,"winner":"D","color":"#4292c6"},"95":{"dem_votes":4504,"rep_votes":2661,"other_votes":3,"total_votes":7168,"dem_candidate":"Krystle Matthews","rep_candidate":"Tim Scott","margin":-1843,"margin_pct":-25.7115,"winner":"D","color":"#4292c6"},"3":{"dem_votes":3132,"rep_votes":7245,"other_votes":13,"total_votes":10390,"dem_candidate":"Krystle Matthews","rep_candidate":"Tim Scott","margin":4113,"margin_pct":39.5861,"winner":"R","color":"#a50f15"},"4":{"dem_votes":1788,"rep_votes":12042,"other_votes":19,"total_votes":13849,"dem_candidate":"Krystle Matthews","rep_candidate":"Tim Scott","margin":10254,"margin_pct":74.0414,"winner":"R","color":"#67000d"},"5":{"dem_votes":2679,"rep_votes":10956,"other_votes":10,"total_votes":13645,"dem_candidate":"Krystle Matthews","rep_candidate":"Tim Scott","margin":8277,"margin_pct":60.6596,"winner":"R","color":"#67000d"},"78":{"dem_votes":7654,"rep_votes":7037,"other_votes":24,"total_votes":14715,"dem_candidate":"Krystle Matthews","rep_candidate":"Tim Scott","margin":-617,"margin_pct":-4.193,"winner":"D","color":"#c6dbef"},"74":{"dem_votes":6780,"rep_votes":2131,"other_votes":35,"total_votes":8946,"dem_candidate":"Krystle Matthews","rep_candidate":"Tim Scott","margin":-4649,"margin_pct":-51.9674,"winner":"D","color":"#08519c"},"72":{"dem_votes":4702,"rep_votes":2244,"other_votes":30,"total_votes":6976,"dem_candidate":"Krystle Matthews","rep_candidate":"Tim Scott","margin":-2458,"margin_pct":-35.2351,"winner":"D","color":"#2171b5"},"70":{"dem_votes":6788,"rep_votes":2760,"other_votes":5,"total_votes":9553,"dem_candidate":"Krystle Matthews","rep_candidate":"Tim Scott","margin":-4028,"margin_pct":-42.1648,"winner":"D","color":"#08519c"},"77":{"dem_votes":11893,"rep_votes":5280,"other_votes":18,"total_votes":17191,"dem_candidate":"Krystle Matthews","rep_candidate":"Tim Scott","margin":-6613,"margin_pct":-38.4678,"winner":"D","color":"#2171b5"},"79":{"dem_votes":10040,"rep_votes":3390,"other_votes":12,"total_votes":13442,"dem_candidate":"Krystle Matthews","rep_candidate":"Tim Scott","margin":-6650,"margin_pct":-49.4718,"winner":"D","color":"#08519c"},"76":{"dem_votes":6809,"rep_votes":2178,"other_votes":13,"total_votes":9000,"dem_candidate":"Krystle Matthews","rep_candidate":"Tim Scott","margin":-4631,"margin_pct":-51.4556,"winner":"D","color":"#08519c"},"73":{"dem_votes":7027,"rep_votes":2199,"other_votes":6,"total_votes":9232,"dem_candidate":"Krystle Matthews","rep_candidate":"Tim Scott","margin":-4828,"margin_pct":-52.2964,"winner":"D","color":"#08519c"},"75":{"dem_votes":5321,"rep_votes":7064,"other_votes":50,"total_votes":12435,"dem_candidate":"Krystle Matthews","rep_candidate":"Tim Scott","margin":1743,"margin_pct":14.0169,"winner":"R","color":"#ef3b2c"},"67":{"dem_votes":4726,"rep_votes":8153,"other_votes":10,"total_votes":12889,"dem_candidate":"Krystle Matthews","rep_candidate":"Tim Scott","margin":3427,"margin_pct":26.5886,"winner":"R","color":"#cb181d"},"34":{"dem_votes":5306,"rep_votes":8062,"other_votes":19,"total_votes":13387,"dem_candidate":"Krystle Matthews","rep_candidate":"Tim Scott","margin":2756,"margin_pct":20.5871,"winner":"R","color":"#cb181d"},"31":{"dem_votes":3512,"rep_votes":1327,"other_votes":5,"total_votes":4844,"dem_candidate":"Krystle Matthews","rep_candidate":"Tim Scott","margin":-2185,"margin_pct":-45.1073,"winner":"D","color":"#08519c"},"32":{"dem_votes":3106,"rep_votes":7906,"other_votes":20,"total_votes":11032,"dem_candidate":"Krystle Matthews","rep_candidate":"Tim Scott","margin":4800,"margin_pct":43.5098,"winner":"R","color":"#67000d"},"33":{"dem_votes":2906,"rep_votes":10515,"other_votes":7,"total_votes":13428,"dem_candidate":"Krystle Matthews","rep_candidate":"Tim Scott","margin":7609,"margin_pct":56.6652,"winner":"R","color":"#67000d"},"37":{"dem_votes":3350,"rep_votes":8498,"other_votes":13,"total_votes":11861,"dem_candidate":"Krystle Matthews","rep_candidate":"Tim Scott","margin":5148,"margin_pct":43.4027,"winner":"R","color":"#67000d"},"38":{"dem_votes":2741,"rep_votes":12737,"other_votes":13,"total_votes":15491,"dem_candidate":"Krystle Matthews","rep_candidate":"Tim Scott","margin":9996,"margin_pct":64.5278,"winner":"R","color":"#67000d"},"51":{"dem_votes":5650,"rep_votes":2602,"other_votes":11,"total_votes":8263,"dem_candidate":"Krystle Matthews","rep_candidate":"Tim Scott","margin":-3048,"margin_pct":-36.8873,"winner":"D","color":"#2171b5"},"47":{"dem_votes":4477,"rep_votes":12374,"other_votes":14,"total_votes":16865,"dem_candidate":"Krystle Matthews","rep_candidate":"Tim Scott","margin":7897,"margin_pct":46.8248,"winner":"R","color":"#67000d"},"48":{"dem_votes":6698,"rep_votes":11848,"other_votes":13,"total_votes":18559,"dem_candidate":"Krystle Matthews","rep_candidate":"Tim Scott","margin":5150,"margin_pct":27.7493,"winner":"R","color":"#cb181d"},"26":{"dem_votes":6915,"rep_votes":11342,"other_votes":16,"total_votes":18273,"dem_candidate":"Krystle Matthews","rep_candidate":"Tim Scott","margin":4427,"margin_pct":24.227,"winner":"R","color":"#cb181d"},"49":{"dem_votes":5866,"rep_votes":4606,"other_votes":5,"total_votes":10477,"dem_candidate":"Krystle Matthews","rep_candidate":"Tim Scott","margin":-1260,"margin_pct":-12.0263,"winner":"D","color":"#6baed6"},"46":{"dem_votes":5606,"rep_votes":8095,"other_votes":11,"total_votes":13712,"dem_candidate":"Krystle Matthews","rep_candidate":"Tim Scott","margin":2489,"margin_pct":18.152,"winner":"R","color":"#ef3b2c"}}},"meta":{"match_coverage_pct":97.9167,"precinct_rows_total":2256,"precinct_rows_matched":2209}}